Metadata-Version: 1.0
Name: ical2org
Version: 1.2
Summary: Convert iCal files to emacs org-mode data
Home-page: http://www.doughellmann.com/projects/ical2org/
Author: Doug Hellmann
Author-email: doug.hellmann@gmail.com
License: UNKNOWN
Platform: UNKNOWN
Classifier: Development Status :: 5 - Production/Stable
Classifier: License :: OSI Approved :: BSD License
Classifier: Programming Language :: Python
Classifier: Environment :: Console
Classifier: Intended Audience :: End Users/Desktop
Classifier: Operating System :: MacOS :: MacOS X
Classifier: Topic :: Communications
Classifier: Topic :: Office/Business
Classifier: Topic :: Office/Business :: Scheduling
